server.py
win32_mcp_server-1.0.1.dist-info/licenses/LICENSE
win32_mcp_server-1.0.1.dist-info/METADATA
win32_mcp_server-1.0.1.dist-info/WHEEL
win32_mcp_server-1.0.1.dist-info/entry_points.txt
win32_mcp_server-1.0.1.dist-info/top_level.txt
win32_mcp_server-1.0.1.dist-info/RECORD
