Metadata-Version: 2.4
Name: win32-mcp-server
Version: 1.0.1
Summary: Comprehensive Windows automation MCP server for AI agents
Author-email: Randy Northrup <randy@example.com>
License: MIT
Project-URL: Homepage, https://github.com/RandyNorthrup/win32-mcp-server
Project-URL: Repository, https://github.com/RandyNorthrup/win32-mcp-server
Project-URL: Issues, https://github.com/RandyNorthrup/win32-mcp-server/issues
Project-URL: Documentation, https://github.com/RandyNorthrup/win32-mcp-server#readme
Keywords: mcp,windows,automation,ocr,ai
Classifier: Development Status :: 4 - Beta
Classifier: Intended Audience :: Developers
Classifier: License :: OSI Approved :: MIT License
Classifier: Programming Language :: Python :: 3
Classifier: Programming Language :: Python :: 3.10
Classifier: Programming Language :: Python :: 3.11
Classifier: Programming Language :: Python :: 3.12
Classifier: Operating System :: Microsoft :: Windows
Classifier: Topic :: Software Development :: Libraries :: Python Modules
Requires-Python: >=3.10
License-File: LICENSE
Requires-Dist: mcp>=1.0.0
Requires-Dist: mss>=10.0.0
Requires-Dist: pillow>=10.0.0
Requires-Dist: pyautogui>=0.9.54
Requires-Dist: pygetwindow>=0.0.9
Requires-Dist: pyperclip>=1.8.2
Requires-Dist: pytesseract>=0.3.10
Requires-Dist: psutil>=5.9.0
Dynamic: license-file
